setup.cfg
setup.py
tests/__init__.py
tests/test_complete.py
tests/test_exclusive.py
tests/test_from_dict.py
tests/test_twitter.py
yamlious/__init__.py
yamlious.egg-info/PKG-INFO
yamlious.egg-info/SOURCES.txt
yamlious.egg-info/dependency_links.txt
yamlious.egg-info/requires.txt
yamlious.egg-info/top_level.txt
yamlious.egg-info/zip-safe