Metadata-Version: 1.1
Name: yamlious
Version: 0.2.0
Summary: Build voluptuous schema from yaml files
Home-page: https://github.com/cogniteev/yamlious
Author: Cogniteev
Author-email: tech@cogniteev.com
License: Apache license version 2.0
Download-URL: https://github.com/cogniteev/yamlious/tarball/v0.2.0
Keywords: yaml voluptuous schema validation
Platform: UNKNOWN
Classifier: Development Status :: 2 - Pre-Alpha
Classifier: Intended Audience :: Developers
Classifier: License :: OSI Approved :: Apache Software License
Classifier: Topic :: Software Development :: Libraries
Classifier: Topic :: Internet :: WWW/HTTP :: Indexing/Search
Classifier: Programming Language :: Python
Classifier: Programming Language :: Python :: 2.6
Classifier: Programming Language :: Python :: 2.7
Classifier: Programming Language :: Python :: 3.2
Classifier: Programming Language :: Python :: 3.3
Classifier: Programming Language :: Python :: 3.4
Classifier: Operating System :: OS Independent
Classifier: Natural Language :: English
